nos/__init__.py
nos/compat.py
nos/connection.py
nos/exceptions.py
nos/serializer.py
nos/transport.py
nos/client/__init__.py
nos/client/auth.py
nos/client/nos_client.py
nos/client/utils.py
eventlet_nos_python_sdk-1.0.4.dist-info/LICENSE
eventlet_nos_python_sdk-1.0.4.dist-info/METADATA
eventlet_nos_python_sdk-1.0.4.dist-info/WHEEL
eventlet_nos_python_sdk-1.0.4.dist-info/top_level.txt
eventlet_nos_python_sdk-1.0.4.dist-info/RECORD
