Metadata-Version: 2.1
Name: eventlet-nos-python-sdk
Version: 1.0.4
Summary: NetEase Object Storage SDK
Home-page: https://c.163.com/
Author: NOS Developer
Author-email: hzsunjianliang@corp.netease.com
License: MIT License
Platform: UNKNOWN
Classifier: Development Status :: 5 - Production/Stable
Classifier: License :: OSI Approved :: MIT License
Classifier: Intended Audience :: Developers
Classifier: Operating System :: OS Independent
Classifier: Programming Language :: Python
Classifier: Programming Language :: Python :: 2
Classifier: Programming Language :: Python :: 2.6
Classifier: Programming Language :: Python :: 2.7
Requires-Dist: urllib3 (<2.0,>=1.8)
Requires-Dist: eventlet (<=0.27.0)
Requires-Dist: certifi
